pytest_unmarked.py
pytest_unmarked-1.1.dist-info/entry_points.txt
pytest_unmarked-1.1.dist-info/METADATA
pytest_unmarked-1.1.dist-info/WHEEL
pytest_unmarked-1.1.dist-info/RECORD
pytest_unmarked-1.1.dist-info/metadata.json
pytest_unmarked-1.1.dist-info/top_level.txt
pytest_unmarked-1.1.dist-info/DESCRIPTION.rst
